LICENSE
MANIFEST.in
README.rst
requirements.txt
setup.cfg
setup.py
test-requirements.txt
python_symphony.egg-info/PKG-INFO
python_symphony.egg-info/SOURCES.txt
python_symphony.egg-info/dependency_links.txt
python_symphony.egg-info/not-zip-safe
python_symphony.egg-info/requires.txt
python_symphony.egg-info/top_level.txt
symphony/__init__.py
symphony/Agent/__init__.py
symphony/Agent/base.py
symphony/Auth/__init__.py
symphony/Config/__init__.py
symphony/Crypt/__init__.py
symphony/Mml/__init__.py
symphony/Pod/__init__.py
symphony/Pod/admin.py
symphony/Pod/base.py
symphony/Pod/connections.py
symphony/Pod/groups.py
symphony/Pod/streams.py
symphony/Pod/users.py
symphony/RESTful/__init__.py
symphony/RESTful/nopkcs.py
symphony/RESTful/pkcs.py