Metadata-Version: 1.1
Name: python-symphony
Version: 0.2.6
Summary: python module for symphony chat
Home-page: https://github.com/symphonyoss/python-symphony
Author: Matt Joyce
Author-email: matt@joyce.nyc
License: Apache 2.0
Keywords: symphony chat api python module
Platform: UNKNOWN
Classifier: Development Status :: 3 - Alpha
Classifier: Intended Audience :: Developers
Classifier: Topic :: Software Development :: Build Tools
Classifier: License :: OSI Approved :: Apache Software License
Classifier: Programming Language :: Python :: 2
Classifier: Programming Language :: Python :: 2.7
Classifier: Programming Language :: Python :: 3
Classifier: Programming Language :: Python :: 3.4
